{"Week 1, 2020": "C:\\Users\\milla\\Downloads\\Weekly Sales Report - 0215 - Forbes Ave, Pittsburgh, PA   - Week 1, 2020.xls", "Week 1, 2023": "C:\\Users\\milla\\Downloads\\Weekly Sales Report - 0215 - Forbes Ave, Pittsburgh, PA   - Week 1, 2023.xls", "Week 2, 2020": "C:\\Users\\milla\\Downloads\\Weekly Sales Report - 0215 - Forbes Ave, Pittsburgh, PA   - Week 2, 2020.xls", "Week 4, 2019": "C:\\Users\\milla\\Downloads\\Weekly Sales Report - 0215 - Forbes Ave, Pittsburgh, PA   - Week 4, 2019.xls", "Week 47, 2023": "C:\\Users\\milla\\Downloads\\Weekly Sales Report - 0215 - Forbes Ave, Pittsburgh, PA   - Week 47, 2023.xls", "Week 48, 2023": "C:\\Users\\milla\\Downloads\\Weekly Sales Report - 0215 - Forbes Ave, Pittsburgh, PA   - Week 48, 2023.xls", "Week 49, 2023": "C:\\Users\\milla\\Downloads\\Weekly Sales Report - 0215 - Forbes Ave, Pittsburgh, PA   - Week 49, 2023.xls", "Week 5, 2019": "C:\\Users\\milla\\Downloads\\Weekly Sales Report - 0215 - Forbes Ave, Pittsburgh, PA   - Week 5, 2019.xls", "Week 50, 2023": "C:\\Users\\milla\\Downloads\\Weekly Sales Report - 0215 - Forbes Ave, Pittsburgh, PA   - Week 50, 2023.xls", "Week 51, 2018": "C:\\Users\\milla\\Downloads\\Weekly Sales Report - 0215 - Forbes Ave, Pittsburgh, PA   - Week 51, 2018.xls", "Week 51, 2023": "C:\\Users\\milla\\Downloads\\Weekly Sales Report - 0215 - Forbes Ave, Pittsburgh, PA   - Week 51, 2023.xls", "Week 52, 2023": "C:\\Users\\milla\\Downloads\\Weekly Sales Report - 0215 - Forbes Ave, Pittsburgh, PA   - Week 52, 2023.xls"}